bilibili_up/AV.py
bilibili_up/BV.py
bilibili_up/__init__.py
bilibili_up-2.0.0.0.dist-info/METADATA
bilibili_up-2.0.0.0.dist-info/WHEEL
bilibili_up-2.0.0.0.dist-info/top_level.txt
bilibili_up-2.0.0.0.dist-info/RECORD
